<?xml version="1.0" encoding="utf-8"?>
<TextureAtlas imagePath="Jumpscr03.png">
	<!-- Created with Adobe Animate version 21.0.1.37179 -->
	<!-- http://www.adobe.com/products/animate.html -->
	<SubTexture name="U instance 10000" x="5" y="5" width="275" height="124" frameX="-152" frameY="0" frameWidth="518.5" frameHeight="362"/>
	<SubTexture name="U instance 10001" x="285" y="5" width="285.5" height="273" frameX="-179" frameY="0" frameWidth="518.5" frameHeight="362"/>
	<SubTexture name="U instance 10002" x="575.5" y="5" width="386" height="362" frameX="-132.5" frameY="0" frameWidth="518.5" frameHeight="362"/>
	<SubTexture name="U instance 10003" x="575.5" y="5" width="386" height="362" frameX="-132.5" frameY="0" frameWidth="518.5" frameHeight="362"/>
	<SubTexture name="U instance 10004" x="966.5" y="5" width="375.5" height="362" frameX="-143" frameY="0" frameWidth="518.5" frameHeight="362"/>
	<SubTexture name="U instance 10005" x="966.5" y="5" width="375.5" height="362" frameX="-143" frameY="0" frameWidth="518.5" frameHeight="362"/>
	<SubTexture name="U instance 10006" x="1347" y="5" width="392" height="362" frameX="-126.5" frameY="0" frameWidth="518.5" frameHeight="362"/>
	<SubTexture name="U instance 10007" x="1347" y="5" width="392" height="362" frameX="-126.5" frameY="0" frameWidth="518.5" frameHeight="362"/>
	<SubTexture name="U instance 10008" x="5" y="372" width="417" height="362" frameX="-101.5" frameY="0" frameWidth="518.5" frameHeight="362"/>
	<SubTexture name="U instance 10009" x="5" y="372" width="417" height="362" frameX="-101.5" frameY="0" frameWidth="518.5" frameHeight="362"/>
	<SubTexture name="U instance 10010" x="427" y="372" width="258.5" height="359.5" frameX="-177.5" frameY="0" frameWidth="518.5" frameHeight="362"/>
	<SubTexture name="U instance 10011" x="427" y="372" width="258.5" height="359.5" frameX="-177.5" frameY="0" frameWidth="518.5" frameHeight="362"/>
	<SubTexture name="U instance 10012" x="690.5" y="372" width="393" height="362" frameX="-42" frameY="0" frameWidth="518.5" frameHeight="362"/>
	<SubTexture name="U instance 10013" x="690.5" y="372" width="393" height="362" frameX="-42" frameY="0" frameWidth="518.5" frameHeight="362"/>
	<SubTexture name="U instance 10014" x="1088.5" y="372" width="432" height="362" frameX="-7.5" frameY="0" frameWidth="518.5" frameHeight="362"/>
	<SubTexture name="U instance 10015" x="1088.5" y="372" width="432" height="362" frameX="-7.5" frameY="0" frameWidth="518.5" frameHeight="362"/>
	<SubTexture name="U instance 10016" x="1525.5" y="372" width="443" height="362" frameX="0" frameY="0" frameWidth="518.5" frameHeight="362"/>
	<SubTexture name="U instance 10017" x="1525.5" y="372" width="443" height="362" frameX="0" frameY="0" frameWidth="518.5" frameHeight="362"/>
	<SubTexture name="U instance 10018" x="5" y="739" width="388.5" height="362" frameX="-58.5" frameY="0" frameWidth="518.5" frameHeight="362"/>
	<SubTexture name="U instance 10019" x="5" y="739" width="388.5" height="362" frameX="-58.5" frameY="0" frameWidth="518.5" frameHeight="362"/>
	<SubTexture name="U instance 10020" x="398.5" y="739" width="339" height="362" frameX="-127" frameY="0" frameWidth="518.5" frameHeight="362"/>
	<SubTexture name="U instance 10021" x="398.5" y="739" width="339" height="362" frameX="-127" frameY="0" frameWidth="518.5" frameHeight="362"/>
	<SubTexture name="U instance 10022" x="742.5" y="739" width="310.5" height="362" frameX="-147.5" frameY="0" frameWidth="518.5" frameHeight="362"/>
	<SubTexture name="U instance 10023" x="742.5" y="739" width="310.5" height="362" frameX="-147.5" frameY="0" frameWidth="518.5" frameHeight="362"/>
	<SubTexture name="U instance 10024" x="1058" y="739" width="293.5" height="362" frameX="-160" frameY="0" frameWidth="518.5" frameHeight="362"/>
	<SubTexture name="U instance 10025" x="1058" y="739" width="293.5" height="362" frameX="-160" frameY="0" frameWidth="518.5" frameHeight="362"/>
	<SubTexture name="U instance 10026" x="1356.5" y="739" width="285.5" height="362" frameX="-167" frameY="0" frameWidth="518.5" frameHeight="362"/>
	<SubTexture name="U instance 10027" x="1356.5" y="739" width="285.5" height="362" frameX="-167" frameY="0" frameWidth="518.5" frameHeight="362"/>
	<SubTexture name="U instance 10028" x="1647" y="739" width="285.5" height="362" frameX="-173" frameY="0" frameWidth="518.5" frameHeight="362"/>
	<SubTexture name="U instance 10029" x="1647" y="739" width="285.5" height="362" frameX="-173" frameY="0" frameWidth="518.5" frameHeight="362"/>
	<SubTexture name="U instance 10030" x="5" y="1106" width="259.5" height="327.5" frameX="-195" frameY="0" frameWidth="518.5" frameHeight="362"/>
	<SubTexture name="U instance 10031" x="5" y="1106" width="259.5" height="327.5" frameX="-195" frameY="0" frameWidth="518.5" frameHeight="362"/>
	<SubTexture name="U instance 10032" x="269.5" y="1106" width="221.5" height="294.5" frameX="-226" frameY="0" frameWidth="518.5" frameHeight="362"/>
	<SubTexture name="U instance 10033" x="496" y="1106" width="159.5" height="216.5" frameX="-299" frameY="0" frameWidth="518.5" frameHeight="362"/>
	<SubTexture name="U instance 10034" x="660.5" y="1106" width="161.5" height="92.5" frameX="-329" frameY="0" frameWidth="518.5" frameHeight="362"/>
	<SubTexture name="U instance 10035" x="827" y="1106" width="0" height="0" frameX="293.5" frameY="-102" frameWidth="518.5" frameHeight="362"/>
	<SubTexture name="U instance 10036" x="827" y="1106" width="0" height="0" frameX="293.5" frameY="-102" frameWidth="518.5" frameHeight="362"/>
	<SubTexture name="U instance 10037" x="827" y="1106" width="0" height="0" frameX="293.5" frameY="-102" frameWidth="518.5" frameHeight="362"/>
	<SubTexture name="U instance 10038" x="827" y="1106" width="0" height="0" frameX="293.5" frameY="-102" frameWidth="518.5" frameHeight="362"/>
</TextureAtlas>
