{"name":null,"assets":"aoy4:pathy34:assets%2Fshared%2Fimages%2Fbad.pngy4:sizei4802y4:typey5:IMAGEy2:idR1y7:preloadtgoR0y69:assets%2Fshared%2Fimages%2Fcharacters%2FBOYFRIEND_NUBERT_GAMEOVER.pngR2i168319R3R4R5R7R6tgoR0y69:assets%2Fshared%2Fimages%2Fcharacters%2FBOYFRIEND_NUBERT_GAMEOVER.xmlR2i20040R3y4:TEXTR5R8R6tgoR0y48:assets%2Fshared%2Fimages%2Fcharacters%2FnoGF.pngR2i9957R3R4R5R10R6tgoR0y48:assets%2Fshared%2Fimages%2Fcharacters%2FnoGF.xmlR2i31207R3R9R5R11R6tgoR0y36:assets%2Fshared%2Fimages%2Fcombo.pngR2i5755R3R4R5R12R6tgoR0y41:assets%2Fshared%2Fimages%2FeventArrow.pngR2i3698R3R4R5R13R6tgoR0y33:assets%2Fshared%2Fimages%2Fgo.pngR2i5935R3R4R5R14R6tgoR0y35:assets%2Fshared%2Fimages%2Fgood.pngR2i5124R3R4R5R15R6tgoR0y37:assets%2Fshared%2Fimages%2Fgrafix.pngR2i47224R3R4R5R16R6tgoR0y40:assets%2Fshared%2Fimages%2FhealthBar.pngR2i260R3R4R5R17R6tgoR0y45:assets%2Fshared%2Fimages%2Fimages-go-here.txtR2zR3R9R5R18R6tgoR0y47:assets%2Fshared%2Fimages%2FpauseAlt%2FbfLol.pngR2i14091R3R4R5R19R6tgoR0y47:assets%2Fshared%2Fimages%2FpauseAlt%2FbfLol.xmlR2i3106R3R9R5R20R6tgoR0y49:assets%2Fshared%2Fimages%2FpauseAlt%2FpauseBG.pngR2i44523R3R4R5R21R6tgoR0y49:assets%2Fshared%2Fimages%2FpauseAlt%2FpauseUI.pngR2i18335R3R4R5R22R6tgoR0y49:assets%2Fshared%2Fimages%2FpauseAlt%2FpauseUI.xmlR2i560R3R9R5R23R6tgoR0y36:assets%2Fshared%2Fimages%2Fready.pngR2i13424R3R4R5R24R6tgoR0y34:assets%2Fshared%2Fimages%2Fset.pngR2i10928R3R4R5R25R6tgoR0y35:assets%2Fshared%2Fimages%2Fshit.pngR2i6713R3R4R5R26R6tgoR0y35:assets%2Fshared%2Fimages%2Fsick.pngR2i7500R3R4R5R27R6tgoR0y40:assets%2Fshared%2Fimages%2Fstageback.pngR2i1074770R3R4R5R28R6tgoR0y44:assets%2Fshared%2Fimages%2Fstagecurtains.pngR2i630R3R4R5R29R6tgoR0y42:assets%2Fshared%2Fimages%2Fstage_light.pngR2i115R3R4R5R30R6tgoR0y38:assets%2Fshared%2Fimages%2FtimeBar.pngR2i269R3R4R5R31R6tgoR2i902725R3y5:SOUNDR5y39:assets%2Fshared%2Fmusic%2Fbreakfast.oggy9:pathGroupaR33hR6tgoR2i552833R3R32R5y38:assets%2Fshared%2Fmusic%2FgameOver.oggR34aR35hR6tgoR2i96647R3R32R5y41:assets%2Fshared%2Fmusic%2FgameOverEnd.oggR34aR36hR6tgoR2i5816R3R32R5y36:assets%2Fshared%2Fsounds%2FANGRY.oggR34aR37hR6tgoR2i41935R3R32R5y45:assets%2Fshared%2Fsounds%2FANGRY_TEXT_BOX.oggR34aR38hR6tgoR2i15125R3R32R5y40:assets%2Fshared%2Fsounds%2Fbadnoise1.oggR34aR39hR6tgoR2i15321R3R32R5y40:assets%2Fshared%2Fsounds%2Fbadnoise2.oggR34aR40hR6tgoR2i15106R3R32R5y40:assets%2Fshared%2Fsounds%2Fbadnoise3.oggR34aR41hR6tgoR2i7202R3R32R5y43:assets%2Fshared%2Fsounds%2FChartingTick.oggR34aR42hR6tgoR2i8237R3R32R5y40:assets%2Fshared%2Fsounds%2FclickText.oggR34aR43hR6tgoR2i6041R3R32R5y39:assets%2Fshared%2Fsounds%2Fdialogue.oggR34aR44hR6tgoR2i9134R3R32R5y44:assets%2Fshared%2Fsounds%2FdialogueClose.oggR34aR45hR6tgoR2i58499R3R32R5y43:assets%2Fshared%2Fsounds%2Ffnf_loss_sfx.oggR34aR46hR6tgoR2i7817R3R32R5y35:assets%2Fshared%2Fsounds%2FGF_1.oggR34aR47hR6tgoR2i8253R3R32R5y35:assets%2Fshared%2Fsounds%2FGF_2.oggR34aR48hR6tgoR2i8585R3R32R5y35:assets%2Fshared%2Fsounds%2FGF_3.oggR34aR49hR6tgoR2i8048R3R32R5y35:assets%2Fshared%2Fsounds%2FGF_4.oggR34aR50hR6tgoR2i12118R3R32R5y37:assets%2Fshared%2Fsounds%2Fintro1.oggR34aR51hR6tgoR2i11627R3R32R5y37:assets%2Fshared%2Fsounds%2Fintro2.oggR34aR52hR6tgoR2i11867R3R32R5y37:assets%2Fshared%2Fsounds%2Fintro3.oggR34aR53hR6tgoR2i11284R3R32R5y38:assets%2Fshared%2Fsounds%2FintroGo.oggR34aR54hR6tgoR2i5878R3R32R5y45:assets%2Fshared%2Fsounds%2FMetronome_Tick.oggR34aR55hR6tgoR2i9152R3R32R5y40:assets%2Fshared%2Fsounds%2Fmissnote1.oggR34aR56hR6tgoR2i9804R3R32R5y40:assets%2Fshared%2Fsounds%2Fmissnote2.oggR34aR57hR6tgoR2i10581R3R32R5y40:assets%2Fshared%2Fsounds%2Fmissnote3.oggR34aR58hR6tgoR0y45:assets%2Fshared%2Fsounds%2Fsounds-go-here.txtR2zR3R9R5R59R6tgoR2i140454R3R32R5y40:assets%2Fshared%2Fsounds%2FsoundTest.oggR34aR60hR6tgh","rootPath":"../","version":2,"libraryArgs":[],"libraryType":null}