<?xml version="1.0" encoding="utf-8"?>
<TextureAtlas imagePath="Sour.png">
	<!-- Created with Adobe Animate version 24.0.2.12 -->
	<!-- http://www.adobe.com/products/animate.html -->
	<SubTexture name="Sour Idle0000" x="5" y="5" width="699" height="621" frameX="0" frameY="-17" frameWidth="710" frameHeight="638"/>
	<SubTexture name="Sour Idle0001" x="5" y="5" width="699" height="621" frameX="0" frameY="-17" frameWidth="710" frameHeight="638"/>
	<SubTexture name="Sour Idle0002" x="709" y="5" width="703" height="606" frameX="-1" frameY="-32" frameWidth="710" frameHeight="638"/>
	<SubTexture name="Sour Idle0003" x="709" y="5" width="703" height="606" frameX="-1" frameY="-32" frameWidth="710" frameHeight="638"/>
	<SubTexture name="Sour Idle0004" x="1417" y="5" width="701" height="613" frameX="-4" frameY="-24" frameWidth="710" frameHeight="638"/>
	<SubTexture name="Sour Idle0005" x="1417" y="5" width="701" height="613" frameX="-4" frameY="-24" frameWidth="710" frameHeight="638"/>
	<SubTexture name="Sour Idle0006" x="5" y="631" width="698" height="626" frameX="-7" frameY="-11" frameWidth="710" frameHeight="638"/>
	<SubTexture name="Sour Idle0007" x="5" y="631" width="698" height="626" frameX="-7" frameY="-11" frameWidth="710" frameHeight="638"/>
	<SubTexture name="Sour Idle0008" x="708" y="631" width="706" height="636" frameX="-4" frameY="-1" frameWidth="710" frameHeight="638"/>
	<SubTexture name="Sour Idle0009" x="1419" y="631" width="706" height="636" frameX="-4" frameY="-1" frameWidth="710" frameHeight="638"/>
	<SubTexture name="Sour Idle0010" x="5" y="1272" width="706" height="637" frameX="-4" frameY="0" frameWidth="710" frameHeight="638"/>
	<SubTexture name="Sour Idle0011" x="5" y="1272" width="706" height="637" frameX="-4" frameY="0" frameWidth="710" frameHeight="638"/>
	<SubTexture name="Sour Idle0012" x="5" y="1272" width="706" height="637" frameX="-4" frameY="0" frameWidth="710" frameHeight="638"/>
	<SubTexture name="Sour Idle0013" x="5" y="1272" width="706" height="637" frameX="-4" frameY="0" frameWidth="710" frameHeight="638"/>
</TextureAtlas>
