<?xml version="1.0" encoding="utf-8"?>
<TextureAtlas imagePath="mark animation.png">
	<!-- Created with Adobe Animate version 21.0.5.40714 -->
	<!-- http://www.adobe.com/products/animate.html -->
	<SubTexture name="mark showing0000" x="0" y="0" width="696" height="1232" frameX="-9" frameY="-69" frameWidth="1072" frameHeight="1301"/>
	<SubTexture name="mark showing0001" x="696" y="0" width="696" height="1232" frameX="-9" frameY="-69" frameWidth="1072" frameHeight="1301"/>
	<SubTexture name="mark showing0002" x="1392" y="0" width="696" height="1232" frameX="-9" frameY="-69" frameWidth="1072" frameHeight="1301"/>
	<SubTexture name="mark showing0003" x="2088" y="0" width="694" height="1247" frameX="-11" frameY="-54" frameWidth="1072" frameHeight="1301"/>
	<SubTexture name="mark showing0004" x="2782" y="0" width="694" height="1247" frameX="-11" frameY="-54" frameWidth="1072" frameHeight="1301"/>
	<SubTexture name="mark showing0005" x="3476" y="0" width="695" height="1233" frameX="-10" frameY="-68" frameWidth="1072" frameHeight="1301"/>
	<SubTexture name="mark showing0006" x="4171" y="0" width="695" height="1233" frameX="-10" frameY="-68" frameWidth="1072" frameHeight="1301"/>
	<SubTexture name="mark showing0007" x="4866" y="0" width="695" height="1231" frameX="-10" frameY="-70" frameWidth="1072" frameHeight="1301"/>
	<SubTexture name="mark showing0008" x="5561" y="0" width="695" height="1231" frameX="-10" frameY="-70" frameWidth="1072" frameHeight="1301"/>
	<SubTexture name="mark showing0009" x="6256" y="0" width="695" height="1231" frameX="-10" frameY="-70" frameWidth="1072" frameHeight="1301"/>
	<SubTexture name="mark showing0010" x="0" y="0" width="696" height="1232" frameX="-9" frameY="-69" frameWidth="1072" frameHeight="1301"/>
	<SubTexture name="mark showing0011" x="6951" y="0" width="695" height="1231" frameX="-10" frameY="-70" frameWidth="1072" frameHeight="1301"/>
	<SubTexture name="mark showing0012" x="0" y="1247" width="695" height="1231" frameX="-10" frameY="-70" frameWidth="1072" frameHeight="1301"/>
	<SubTexture name="mark showing0013" x="695" y="1247" width="695" height="1231" frameX="-10" frameY="-70" frameWidth="1072" frameHeight="1301"/>
	<SubTexture name="mark showing0014" x="1390" y="1247" width="695" height="1231" frameX="-10" frameY="-70" frameWidth="1072" frameHeight="1301"/>
	<SubTexture name="mark showing0015" x="2085" y="1247" width="695" height="1231" frameX="-10" frameY="-70" frameWidth="1072" frameHeight="1301"/>
	<SubTexture name="mark showing0016" x="2780" y="1247" width="695" height="1231" frameX="-10" frameY="-70" frameWidth="1072" frameHeight="1301"/>
	<SubTexture name="mark showing0017" x="3475" y="1247" width="695" height="1231" frameX="-10" frameY="-70" frameWidth="1072" frameHeight="1301"/>
	<SubTexture name="mark showing0018" x="4170" y="1247" width="695" height="1231" frameX="-10" frameY="-70" frameWidth="1072" frameHeight="1301"/>
	<SubTexture name="mark showing0019" x="4865" y="1247" width="695" height="1231" frameX="-10" frameY="-70" frameWidth="1072" frameHeight="1301"/>
	<SubTexture name="mark showing0020" x="6951" y="0" width="695" height="1231" frameX="-10" frameY="-70" frameWidth="1072" frameHeight="1301"/>
	<SubTexture name="mark showing0021" x="696" y="0" width="696" height="1232" frameX="-9" frameY="-69" frameWidth="1072" frameHeight="1301"/>
	<SubTexture name="mark showing0022" x="1390" y="1247" width="695" height="1231" frameX="-10" frameY="-70" frameWidth="1072" frameHeight="1301"/>
	<SubTexture name="mark showing0023" x="1392" y="0" width="696" height="1232" frameX="-9" frameY="-69" frameWidth="1072" frameHeight="1301"/>
	<SubTexture name="mark showing0024" x="2780" y="1247" width="695" height="1231" frameX="-10" frameY="-70" frameWidth="1072" frameHeight="1301"/>
	<SubTexture name="mark showing0025" x="3475" y="1247" width="695" height="1231" frameX="-10" frameY="-70" frameWidth="1072" frameHeight="1301"/>
	<SubTexture name="mark showing0026" x="4170" y="1247" width="695" height="1231" frameX="-10" frameY="-70" frameWidth="1072" frameHeight="1301"/>
	<SubTexture name="mark showing0027" x="4865" y="1247" width="695" height="1231" frameX="-10" frameY="-70" frameWidth="1072" frameHeight="1301"/>
	<SubTexture name="mark showing0028" x="6951" y="0" width="695" height="1231" frameX="-10" frameY="-70" frameWidth="1072" frameHeight="1301"/>
	<SubTexture name="mark showing0029" x="695" y="1247" width="695" height="1231" frameX="-10" frameY="-70" frameWidth="1072" frameHeight="1301"/>
	<SubTexture name="mark showing0030" x="1390" y="1247" width="695" height="1231" frameX="-10" frameY="-70" frameWidth="1072" frameHeight="1301"/>
	<SubTexture name="mark showing0031" x="2085" y="1247" width="695" height="1231" frameX="-10" frameY="-70" frameWidth="1072" frameHeight="1301"/>
	<SubTexture name="mark showing0032" x="2780" y="1247" width="695" height="1231" frameX="-10" frameY="-70" frameWidth="1072" frameHeight="1301"/>
	<SubTexture name="mark showing0033" x="3475" y="1247" width="695" height="1231" frameX="-10" frameY="-70" frameWidth="1072" frameHeight="1301"/>
	<SubTexture name="mark showing0034" x="4170" y="1247" width="695" height="1231" frameX="-10" frameY="-70" frameWidth="1072" frameHeight="1301"/>
	<SubTexture name="mark showing0035" x="4865" y="1247" width="695" height="1231" frameX="-10" frameY="-70" frameWidth="1072" frameHeight="1301"/>
	<SubTexture name="mark showing0036" x="5560" y="1247" width="695" height="1227" frameX="-10" frameY="-74" frameWidth="1072" frameHeight="1301"/>
	<SubTexture name="mark showing0037" x="6255" y="1247" width="695" height="1227" frameX="-10" frameY="-74" frameWidth="1072" frameHeight="1301"/>
	<SubTexture name="mark showing0038" x="6950" y="1247" width="695" height="1245" frameX="-10" frameY="-56" frameWidth="1072" frameHeight="1301"/>
	<SubTexture name="mark showing0039" x="0" y="2492" width="695" height="1245" frameX="-10" frameY="-56" frameWidth="1072" frameHeight="1301"/>
	<SubTexture name="mark showing0040" x="2780" y="1247" width="695" height="1231" frameX="-10" frameY="-70" frameWidth="1072" frameHeight="1301"/>
	<SubTexture name="mark showing0041" x="3475" y="1247" width="695" height="1231" frameX="-10" frameY="-70" frameWidth="1072" frameHeight="1301"/>
	<SubTexture name="mark showing0042" x="695" y="2492" width="695" height="1244" frameX="-10" frameY="-57" frameWidth="1072" frameHeight="1301"/>
	<SubTexture name="mark showing0043" x="1390" y="2492" width="695" height="1244" frameX="-10" frameY="-57" frameWidth="1072" frameHeight="1301"/>
	<SubTexture name="mark showing0044" x="2085" y="2492" width="695" height="1167" frameX="-10" frameY="-134" frameWidth="1072" frameHeight="1301"/>
	<SubTexture name="mark showing0045" x="2780" y="2492" width="695" height="1167" frameX="-10" frameY="-134" frameWidth="1072" frameHeight="1301"/>
	<SubTexture name="mark showing0046" x="0" y="0" width="696" height="1232" frameX="-9" frameY="-69" frameWidth="1072" frameHeight="1301"/>
	<SubTexture name="mark showing0047" x="696" y="0" width="696" height="1232" frameX="-9" frameY="-69" frameWidth="1072" frameHeight="1301"/>
	<SubTexture name="mark showing0048" x="1392" y="0" width="696" height="1232" frameX="-9" frameY="-69" frameWidth="1072" frameHeight="1301"/>
	<SubTexture name="mark showing0049" x="0" y="0" width="696" height="1232" frameX="-9" frameY="-69" frameWidth="1072" frameHeight="1301"/>
	<SubTexture name="mark showing0050" x="696" y="0" width="696" height="1232" frameX="-9" frameY="-69" frameWidth="1072" frameHeight="1301"/>
	<SubTexture name="mark showing0051" x="3475" y="2492" width="695" height="1244" frameX="-10" frameY="-57" frameWidth="1072" frameHeight="1301"/>
	<SubTexture name="mark showing0052" x="4170" y="2492" width="695" height="1244" frameX="-10" frameY="-57" frameWidth="1072" frameHeight="1301"/>
	<SubTexture name="mark showing0053" x="4865" y="2492" width="695" height="1242" frameX="-10" frameY="-59" frameWidth="1072" frameHeight="1301"/>
	<SubTexture name="mark showing0054" x="5560" y="2492" width="695" height="1242" frameX="-10" frameY="-59" frameWidth="1072" frameHeight="1301"/>
	<SubTexture name="mark showing0055" x="2085" y="1247" width="695" height="1231" frameX="-10" frameY="-70" frameWidth="1072" frameHeight="1301"/>
	<SubTexture name="mark showing0056" x="2780" y="1247" width="695" height="1231" frameX="-10" frameY="-70" frameWidth="1072" frameHeight="1301"/>
	<SubTexture name="mark showing0057" x="5561" y="0" width="695" height="1231" frameX="-10" frameY="-70" frameWidth="1072" frameHeight="1301"/>
	<SubTexture name="mark showing0058" x="6255" y="2492" width="695" height="1231" frameX="-10" frameY="-70" frameWidth="1072" frameHeight="1301"/>
	<SubTexture name="mark showing0059" x="6950" y="2492" width="695" height="1231" frameX="-10" frameY="-70" frameWidth="1072" frameHeight="1301"/>
	<SubTexture name="mark showing0060" x="0" y="3737" width="695" height="1231" frameX="-10" frameY="-70" frameWidth="1072" frameHeight="1301"/>
	<SubTexture name="mark showing0061" x="695" y="1247" width="695" height="1231" frameX="-10" frameY="-70" frameWidth="1072" frameHeight="1301"/>
	<SubTexture name="mark showing0062" x="1390" y="1247" width="695" height="1231" frameX="-10" frameY="-70" frameWidth="1072" frameHeight="1301"/>
	<SubTexture name="mark showing0063" x="2085" y="1247" width="695" height="1231" frameX="-10" frameY="-70" frameWidth="1072" frameHeight="1301"/>
	<SubTexture name="mark showing0064" x="2780" y="1247" width="695" height="1231" frameX="-10" frameY="-70" frameWidth="1072" frameHeight="1301"/>
	<SubTexture name="mark showing0065" x="3475" y="1247" width="695" height="1231" frameX="-10" frameY="-70" frameWidth="1072" frameHeight="1301"/>
	<SubTexture name="mark showing0066" x="0" y="0" width="696" height="1232" frameX="-9" frameY="-69" frameWidth="1072" frameHeight="1301"/>
	<SubTexture name="mark showing0067" x="695" y="3737" width="696" height="1262" frameX="-9" frameY="-39" frameWidth="1072" frameHeight="1301"/>
	<SubTexture name="mark showing0068" x="1391" y="3737" width="694" height="1281" frameX="-9" frameY="-20" frameWidth="1072" frameHeight="1301"/>
	<SubTexture name="mark showing0069" x="2085" y="3737" width="694" height="1281" frameX="-9" frameY="-20" frameWidth="1072" frameHeight="1301"/>
	<SubTexture name="mark showing0070" x="2779" y="3737" width="694" height="1266" frameX="-8" frameY="-35" frameWidth="1072" frameHeight="1301"/>
	<SubTexture name="mark showing0071" x="3473" y="3737" width="694" height="1266" frameX="-8" frameY="-35" frameWidth="1072" frameHeight="1301"/>
	<SubTexture name="mark showing0072" x="4167" y="3737" width="694" height="1253" frameX="-9" frameY="-48" frameWidth="1072" frameHeight="1301"/>
	<SubTexture name="mark showing0073" x="4861" y="3737" width="694" height="1253" frameX="-9" frameY="-48" frameWidth="1072" frameHeight="1301"/>
	<SubTexture name="mark showing0074" x="5555" y="3737" width="694" height="1253" frameX="-9" frameY="-48" frameWidth="1072" frameHeight="1301"/>
	<SubTexture name="mark showing0075" x="6249" y="3737" width="694" height="1253" frameX="-9" frameY="-48" frameWidth="1072" frameHeight="1301"/>
	<SubTexture name="mark showing0076" x="6943" y="3737" width="694" height="1287" frameX="-9" frameY="-14" frameWidth="1072" frameHeight="1301"/>
	<SubTexture name="mark showing0077" x="0" y="5024" width="694" height="1287" frameX="-9" frameY="-14" frameWidth="1072" frameHeight="1301"/>
	<SubTexture name="mark showing0078" x="694" y="5024" width="694" height="1243" frameX="-9" frameY="-58" frameWidth="1072" frameHeight="1301"/>
	<SubTexture name="mark showing0079" x="6249" y="3737" width="694" height="1253" frameX="-9" frameY="-48" frameWidth="1072" frameHeight="1301"/>
	<SubTexture name="mark showing0080" x="4167" y="3737" width="694" height="1253" frameX="-9" frameY="-48" frameWidth="1072" frameHeight="1301"/>
	<SubTexture name="mark showing0081" x="695" y="3737" width="696" height="1262" frameX="-8" frameY="-38" frameWidth="1072" frameHeight="1301"/>
	<SubTexture name="mark showing0082" x="1388" y="5024" width="696" height="1262" frameX="-8" frameY="-39" frameWidth="1072" frameHeight="1301"/>
	<SubTexture name="mark showing0083" x="2084" y="5024" width="696" height="1262" frameX="-8" frameY="-39" frameWidth="1072" frameHeight="1301"/>
	<SubTexture name="mark showing0084" x="4167" y="3737" width="694" height="1253" frameX="-9" frameY="-48" frameWidth="1072" frameHeight="1301"/>
	<SubTexture name="mark showing0085" x="2780" y="5024" width="694" height="1291" frameX="-9" frameY="-10" frameWidth="1072" frameHeight="1301"/>
	<SubTexture name="mark showing0086" x="3474" y="5024" width="1071" height="1301" frameX="0" frameY="0" frameWidth="1072" frameHeight="1301"/>
	<SubTexture name="mark showing0087" x="4545" y="5024" width="1071" height="1301" frameX="0" frameY="0" frameWidth="1072" frameHeight="1301"/>
	<SubTexture name="mark showing0088" x="5616" y="5024" width="1071" height="1301" frameX="0" frameY="0" frameWidth="1072" frameHeight="1301"/>
	<SubTexture name="mark showing0089" x="6687" y="5024" width="1071" height="1301" frameX="0" frameY="0" frameWidth="1072" frameHeight="1301"/>
	<SubTexture name="mark showing0090" x="0" y="6325" width="1071" height="1301" frameX="0" frameY="0" frameWidth="1072" frameHeight="1301"/>
	<SubTexture name="mark showing0091" x="1071" y="6325" width="1071" height="1301" frameX="0" frameY="0" frameWidth="1072" frameHeight="1301"/>
	<SubTexture name="mark showing0092" x="2142" y="6325" width="1071" height="1301" frameX="0" frameY="0" frameWidth="1072" frameHeight="1301"/>
	<SubTexture name="mark showing0093" x="3213" y="6325" width="1063" height="1296" frameX="-9" frameY="-5" frameWidth="1072" frameHeight="1301"/>
	<SubTexture name="mark showing0094" x="4276" y="6325" width="1063" height="1225" frameX="-9" frameY="-76" frameWidth="1072" frameHeight="1301"/>
	<SubTexture name="mark showing0095" x="5339" y="6325" width="1063" height="1239" frameX="-9" frameY="-62" frameWidth="1072" frameHeight="1301"/>
	<SubTexture name="mark showing0096" x="6402" y="6325" width="1063" height="1296" frameX="-9" frameY="-5" frameWidth="1072" frameHeight="1301"/>
	<SubTexture name="mark showing0097" x="3213" y="6325" width="1063" height="1296" frameX="-9" frameY="-5" frameWidth="1072" frameHeight="1301"/>
	<SubTexture name="mark showing0098" x="4276" y="6325" width="1063" height="1225" frameX="-9" frameY="-76" frameWidth="1072" frameHeight="1301"/>
	<SubTexture name="mark showing0099" x="5339" y="6325" width="1063" height="1239" frameX="-9" frameY="-62" frameWidth="1072" frameHeight="1301"/>
	<SubTexture name="mark showing0100" x="6402" y="6325" width="1063" height="1296" frameX="-9" frameY="-5" frameWidth="1072" frameHeight="1301"/>
	<SubTexture name="mark showing0101" x="3213" y="6325" width="1063" height="1296" frameX="-9" frameY="-5" frameWidth="1072" frameHeight="1301"/>
	<SubTexture name="mark showing0102" x="4276" y="6325" width="1063" height="1225" frameX="-9" frameY="-76" frameWidth="1072" frameHeight="1301"/>
	<SubTexture name="mark showing0103" x="5339" y="6325" width="1063" height="1239" frameX="-9" frameY="-62" frameWidth="1072" frameHeight="1301"/>
	<SubTexture name="mark showing0104" x="6402" y="6325" width="1063" height="1296" frameX="-9" frameY="-5" frameWidth="1072" frameHeight="1301"/>
	<SubTexture name="mark showing0105" x="3213" y="6325" width="1063" height="1296" frameX="-9" frameY="-5" frameWidth="1072" frameHeight="1301"/>
	<SubTexture name="mark showing0106" x="4276" y="6325" width="1063" height="1225" frameX="-9" frameY="-76" frameWidth="1072" frameHeight="1301"/>
	<SubTexture name="mark showing0107" x="5339" y="6325" width="1063" height="1239" frameX="-9" frameY="-62" frameWidth="1072" frameHeight="1301"/>
	<SubTexture name="mark showing0108" x="6402" y="6325" width="1063" height="1296" frameX="-9" frameY="-5" frameWidth="1072" frameHeight="1301"/>
	<SubTexture name="mark showing0109" x="3213" y="6325" width="1063" height="1296" frameX="-9" frameY="-5" frameWidth="1072" frameHeight="1301"/>
	<SubTexture name="mark showing0110" x="4276" y="6325" width="1063" height="1225" frameX="-9" frameY="-76" frameWidth="1072" frameHeight="1301"/>
	<SubTexture name="mark showing0111" x="5339" y="6325" width="1063" height="1239" frameX="-9" frameY="-62" frameWidth="1072" frameHeight="1301"/>
	<SubTexture name="mark showing0112" x="6402" y="6325" width="1063" height="1296" frameX="-9" frameY="-5" frameWidth="1072" frameHeight="1301"/>
	<SubTexture name="mark showing0113" x="3213" y="6325" width="1063" height="1296" frameX="-9" frameY="-5" frameWidth="1072" frameHeight="1301"/>
	<SubTexture name="mark showing0114" x="4276" y="6325" width="1063" height="1225" frameX="-9" frameY="-76" frameWidth="1072" frameHeight="1301"/>
	<SubTexture name="mark showing0115" x="5339" y="6325" width="1063" height="1239" frameX="-9" frameY="-62" frameWidth="1072" frameHeight="1301"/>
	<SubTexture name="mark showing0116" x="6402" y="6325" width="1063" height="1296" frameX="-9" frameY="-5" frameWidth="1072" frameHeight="1301"/>
	<SubTexture name="mark showing0117" x="3213" y="6325" width="1063" height="1296" frameX="-9" frameY="-5" frameWidth="1072" frameHeight="1301"/>
	<SubTexture name="mark showing0118" x="4276" y="6325" width="1063" height="1225" frameX="-9" frameY="-76" frameWidth="1072" frameHeight="1301"/>
	<SubTexture name="mark showing0119" x="5339" y="6325" width="1063" height="1239" frameX="-9" frameY="-62" frameWidth="1072" frameHeight="1301"/>
	<SubTexture name="mark showing0120" x="6402" y="6325" width="1063" height="1296" frameX="-9" frameY="-5" frameWidth="1072" frameHeight="1301"/>
	<SubTexture name="mark showing0121" x="3213" y="6325" width="1063" height="1296" frameX="-9" frameY="-5" frameWidth="1072" frameHeight="1301"/>
	<SubTexture name="mark showing0122" x="4276" y="6325" width="1063" height="1225" frameX="-9" frameY="-76" frameWidth="1072" frameHeight="1301"/>
	<SubTexture name="mark showing0123" x="5339" y="6325" width="1063" height="1239" frameX="-9" frameY="-62" frameWidth="1072" frameHeight="1301"/>
	<SubTexture name="mark showing0124" x="6402" y="6325" width="1063" height="1296" frameX="-9" frameY="-5" frameWidth="1072" frameHeight="1301"/>
</TextureAtlas>
