<?xml version='1.0' encoding='utf-8'?>
<TextureAtlas imagePath="bf-konton.png">
<SubTexture name="bf-konton idle0000" x="4985.5" y="0.0" width="1218.5" height="1015.5" frameX="-541.5" frameY="-183.0" frameWidth="2048.0" frameHeight="1198.5" />
<SubTexture name="bf-konton idle0001" x="4985.5" y="0.0" width="1218.5" height="1015.5" frameX="-541.5" frameY="-183.0" frameWidth="2048.0" frameHeight="1198.5" />
<SubTexture name="bf-konton idle0002" x="3761.0" y="1050.0" width="1218.5" height="1033.0" frameX="-541.5" frameY="-165.5" frameWidth="2048.0" frameHeight="1198.5" />
<SubTexture name="bf-konton idle0003" x="2437.0" y="2152.5" width="1218.5" height="1051.0" frameX="-541.5" frameY="-147.5" frameWidth="2048.0" frameHeight="1198.5" />
<SubTexture name="bf-konton idle0004" x="0.0" y="2152.5" width="1218.5" height="1057.0" frameX="-541.5" frameY="-141.5" frameWidth="2048.0" frameHeight="1198.5" />
<SubTexture name="bf-konton idle0005" x="0.0" y="2152.5" width="1218.5" height="1057.0" frameX="-541.5" frameY="-141.5" frameWidth="2048.0" frameHeight="1198.5" />
<SubTexture name="bf-konton idle0006" x="4985.5" y="0.0" width="1218.5" height="1015.5" frameX="-541.5" frameY="-183.0" frameWidth="2048.0" frameHeight="1198.5" />
<SubTexture name="bf-konton idle0007" x="4985.5" y="0.0" width="1218.5" height="1015.5" frameX="-541.5" frameY="-183.0" frameWidth="2048.0" frameHeight="1198.5" />
<SubTexture name="bf-konton idle0008" x="3761.0" y="1050.0" width="1218.5" height="1033.0" frameX="-541.5" frameY="-165.5" frameWidth="2048.0" frameHeight="1198.5" />
<SubTexture name="bf-konton idle0009" x="2437.0" y="2152.5" width="1218.5" height="1051.0" frameX="-541.5" frameY="-147.5" frameWidth="2048.0" frameHeight="1198.5" />
<SubTexture name="bf-konton idle0010" x="0.0" y="2152.5" width="1218.5" height="1057.0" frameX="-541.5" frameY="-141.5" frameWidth="2048.0" frameHeight="1198.5" />
<SubTexture name="bf-konton idle0011" x="0.0" y="2152.5" width="1218.5" height="1057.0" frameX="-541.5" frameY="-141.5" frameWidth="2048.0" frameHeight="1198.5" />
<SubTexture name="bf-konton idle0012" x="4985.5" y="0.0" width="1218.5" height="1015.5" frameX="-541.5" frameY="-183.0" frameWidth="2048.0" frameHeight="1198.5" />
<SubTexture name="bf-konton idle0013" x="4985.5" y="0.0" width="1218.5" height="1015.5" frameX="-541.5" frameY="-183.0" frameWidth="2048.0" frameHeight="1198.5" />
<SubTexture name="bf-konton idle0014" x="3761.0" y="1050.0" width="1218.5" height="1033.0" frameX="-541.5" frameY="-165.5" frameWidth="2048.0" frameHeight="1198.5" />
<SubTexture name="bf-konton idle0015" x="2437.0" y="2152.5" width="1218.5" height="1051.0" frameX="-541.5" frameY="-147.5" frameWidth="2048.0" frameHeight="1198.5" />
<SubTexture name="bf-konton idle0016" x="0.0" y="2152.5" width="1218.5" height="1057.0" frameX="-541.5" frameY="-141.5" frameWidth="2048.0" frameHeight="1198.5" />
<SubTexture name="bf-konton idle0017" x="0.0" y="2152.5" width="1218.5" height="1057.0" frameX="-541.5" frameY="-141.5" frameWidth="2048.0" frameHeight="1198.5" />
<SubTexture name="bf-konton idle0018" x="4985.5" y="0.0" width="1218.5" height="1015.5" frameX="-541.5" frameY="-183.0" frameWidth="2048.0" frameHeight="1198.5" />
<SubTexture name="bf-konton idle0019" x="4985.5" y="0.0" width="1218.5" height="1015.5" frameX="-541.5" frameY="-183.0" frameWidth="2048.0" frameHeight="1198.5" />
<SubTexture name="bf-konton idle0020" x="3761.0" y="1050.0" width="1218.5" height="1033.0" frameX="-541.5" frameY="-165.5" frameWidth="2048.0" frameHeight="1198.5" />
<SubTexture name="bf-konton idle0021" x="2437.0" y="2152.5" width="1218.5" height="1051.0" frameX="-541.5" frameY="-147.5" frameWidth="2048.0" frameHeight="1198.5" />
<SubTexture name="bf-konton idle0022" x="0.0" y="2152.5" width="1218.5" height="1057.0" frameX="-541.5" frameY="-141.5" frameWidth="2048.0" frameHeight="1198.5" />
<SubTexture name="bf-konton idle0023" x="0.0" y="2152.5" width="1218.5" height="1057.0" frameX="-541.5" frameY="-141.5" frameWidth="2048.0" frameHeight="1198.5" />
<SubTexture name="bf-konton down00000" x="4985.5" y="2016.0" width="1218.5" height="986.5" frameX="-541.5" frameY="-212.0" frameWidth="2048.0" frameHeight="1198.5" />
<SubTexture name="bf-konton down00001" x="4985.5" y="2016.0" width="1218.5" height="986.5" frameX="-541.5" frameY="-212.0" frameWidth="2048.0" frameHeight="1198.5" />
<SubTexture name="bf-konton down00002" x="4985.5" y="1015.5" width="1218.5" height="1000.5" frameX="-541.5" frameY="-198.0" frameWidth="2048.0" frameHeight="1198.5" />
<SubTexture name="bf-konton down00003" x="4985.5" y="1015.5" width="1218.5" height="1000.5" frameX="-541.5" frameY="-198.0" frameWidth="2048.0" frameHeight="1198.5" />
<SubTexture name="bf-konton down00004" x="4985.5" y="1015.5" width="1218.5" height="1000.5" frameX="-541.5" frameY="-198.0" frameWidth="2048.0" frameHeight="1198.5" />
<SubTexture name="bf-konton down00005" x="4985.5" y="1015.5" width="1218.5" height="1000.5" frameX="-541.5" frameY="-198.0" frameWidth="2048.0" frameHeight="1198.5" />
<SubTexture name="bf-konton up00000" x="0.0" y="0.0" width="1218.5" height="1078.5" frameX="-541.5" frameY="-120.0" frameWidth="2048.0" frameHeight="1198.5" />
<SubTexture name="bf-konton up00001" x="0.0" y="0.0" width="1218.5" height="1078.5" frameX="-541.5" frameY="-120.0" frameWidth="2048.0" frameHeight="1198.5" />
<SubTexture name="bf-konton up00002" x="0.0" y="1078.5" width="1218.5" height="1074.0" frameX="-541.5" frameY="-124.5" frameWidth="2048.0" frameHeight="1198.5" />
<SubTexture name="bf-konton up00003" x="0.0" y="1078.5" width="1218.5" height="1074.0" frameX="-541.5" frameY="-124.5" frameWidth="2048.0" frameHeight="1198.5" />
<SubTexture name="bf-konton up00004" x="1218.5" y="1078.5" width="1218.5" height="1069.5" frameX="-541.5" frameY="-129.0" frameWidth="2048.0" frameHeight="1198.5" />
<SubTexture name="bf-konton up00005" x="1218.5" y="1078.5" width="1218.5" height="1069.5" frameX="-541.5" frameY="-129.0" frameWidth="2048.0" frameHeight="1198.5" />
<SubTexture name="bf-konton left00000" x="1227.5" y="3209.5" width="1313.5" height="1033.0" frameX="-418.0" frameY="-165.5" frameWidth="2048.0" frameHeight="1198.5" />
<SubTexture name="bf-konton left00001" x="1227.5" y="3209.5" width="1313.5" height="1033.0" frameX="-418.0" frameY="-165.5" frameWidth="2048.0" frameHeight="1198.5" />
<SubTexture name="bf-konton left00002" x="2439.5" y="0.0" width="1321.5" height="1068.5" frameX="-420.5" frameY="-130.0" frameWidth="2048.0" frameHeight="1198.5" />
<SubTexture name="bf-konton left00003" x="2439.5" y="0.0" width="1321.5" height="1068.5" frameX="-420.5" frameY="-130.0" frameWidth="2048.0" frameHeight="1198.5" />
<SubTexture name="bf-konton left00004" x="2439.5" y="1068.5" width="1315.0" height="1065.0" frameX="-442.0" frameY="-133.5" frameWidth="2048.0" frameHeight="1198.5" />
<SubTexture name="bf-konton left00005" x="2439.5" y="1068.5" width="1315.0" height="1065.0" frameX="-442.0" frameY="-133.5" frameWidth="2048.0" frameHeight="1198.5" />
<SubTexture name="bf-konton right00000" x="3761.0" y="2083.0" width="1224.5" height="1032.0" frameX="-578.0" frameY="-166.5" frameWidth="2048.0" frameHeight="1198.5" />
<SubTexture name="bf-konton right00001" x="3761.0" y="2083.0" width="1224.5" height="1032.0" frameX="-578.0" frameY="-166.5" frameWidth="2048.0" frameHeight="1198.5" />
<SubTexture name="bf-konton right00002" x="3761.0" y="0.0" width="1224.5" height="1050.0" frameX="-565.5" frameY="-148.5" frameWidth="2048.0" frameHeight="1198.5" />
<SubTexture name="bf-konton right00003" x="3761.0" y="0.0" width="1224.5" height="1050.0" frameX="-565.5" frameY="-148.5" frameWidth="2048.0" frameHeight="1198.5" />
<SubTexture name="bf-konton right00004" x="1218.5" y="2152.5" width="1218.5" height="1055.0" frameX="-561.0" frameY="-143.5" frameWidth="2048.0" frameHeight="1198.5" />
<SubTexture name="bf-konton right00005" x="1218.5" y="2152.5" width="1218.5" height="1055.0" frameX="-561.0" frameY="-143.5" frameWidth="2048.0" frameHeight="1198.5" />
<SubTexture name="bf-konton down-miss0000" x="0.0" y="4246.0" width="1244.5" height="985.5" frameX="-517.5" frameY="-213.0" frameWidth="2048.0" frameHeight="1198.5" />
<SubTexture name="bf-konton down-miss0001" x="0.0" y="4246.0" width="1244.5" height="985.5" frameX="-517.5" frameY="-213.0" frameWidth="2048.0" frameHeight="1198.5" />
<SubTexture name="bf-konton down-miss0002" x="0.0" y="4246.0" width="1244.5" height="985.5" frameX="-517.5" frameY="-213.0" frameWidth="2048.0" frameHeight="1198.5" />
<SubTexture name="bf-konton down-miss0003" x="0.0" y="4246.0" width="1244.5" height="985.5" frameX="-517.5" frameY="-213.0" frameWidth="2048.0" frameHeight="1198.5" />
<SubTexture name="bf-konton down-miss0004" x="0.0" y="4246.0" width="1244.5" height="985.5" frameX="-517.5" frameY="-213.0" frameWidth="2048.0" frameHeight="1198.5" />
<SubTexture name="bf-konton right-miss0000" x="0.0" y="3209.5" width="1227.5" height="1036.5" frameX="-578.5" frameY="-162.0" frameWidth="2048.0" frameHeight="1198.5" />
<SubTexture name="bf-konton right-miss0001" x="0.0" y="3209.5" width="1227.5" height="1036.5" frameX="-578.5" frameY="-162.0" frameWidth="2048.0" frameHeight="1198.5" />
<SubTexture name="bf-konton right-miss0002" x="0.0" y="3209.5" width="1227.5" height="1036.5" frameX="-578.5" frameY="-162.0" frameWidth="2048.0" frameHeight="1198.5" />
<SubTexture name="bf-konton right-miss0003" x="0.0" y="3209.5" width="1227.5" height="1036.5" frameX="-578.5" frameY="-162.0" frameWidth="2048.0" frameHeight="1198.5" />
<SubTexture name="bf-konton right-miss0004" x="0.0" y="3209.5" width="1227.5" height="1036.5" frameX="-578.5" frameY="-162.0" frameWidth="2048.0" frameHeight="1198.5" />
<SubTexture name="bf-konton up-miss0000" x="1218.5" y="0.0" width="1221.0" height="1077.0" frameX="-539.5" frameY="-121.5" frameWidth="2048.0" frameHeight="1198.5" />
<SubTexture name="bf-konton up-miss0001" x="1218.5" y="0.0" width="1221.0" height="1077.0" frameX="-539.5" frameY="-121.5" frameWidth="2048.0" frameHeight="1198.5" />
<SubTexture name="bf-konton up-miss0002" x="1218.5" y="0.0" width="1221.0" height="1077.0" frameX="-539.5" frameY="-121.5" frameWidth="2048.0" frameHeight="1198.5" />
<SubTexture name="bf-konton up-miss0003" x="1218.5" y="0.0" width="1221.0" height="1077.0" frameX="-539.5" frameY="-121.5" frameWidth="2048.0" frameHeight="1198.5" />
<SubTexture name="bf-konton up-miss0004" x="1218.5" y="0.0" width="1221.0" height="1077.0" frameX="-539.5" frameY="-121.5" frameWidth="2048.0" frameHeight="1198.5" />
<SubTexture name="bf-konton left-miss0000" x="2541.0" y="3209.5" width="1286.5" height="1031.5" frameX="-439.5" frameY="-167.0" frameWidth="2048.0" frameHeight="1198.5" />
<SubTexture name="bf-konton left-miss0001" x="2541.0" y="3209.5" width="1286.5" height="1031.5" frameX="-439.5" frameY="-167.0" frameWidth="2048.0" frameHeight="1198.5" />
<SubTexture name="bf-konton left-miss0002" x="2541.0" y="3209.5" width="1286.5" height="1031.5" frameX="-439.5" frameY="-167.0" frameWidth="2048.0" frameHeight="1198.5" />
<SubTexture name="bf-konton left-miss0003" x="2541.0" y="3209.5" width="1286.5" height="1031.5" frameX="-439.5" frameY="-167.0" frameWidth="2048.0" frameHeight="1198.5" />
<SubTexture name="bf-konton left-miss0004" x="2541.0" y="3209.5" width="1286.5" height="1031.5" frameX="-439.5" frameY="-167.0" frameWidth="2048.0" frameHeight="1198.5" />
</TextureAtlas>
