<?xml version="1.0" encoding="utf-8"?>
<TextureAtlas imagePath="Spinel_Pibby.png">
	<!-- Created with Adobe Animate version 23.0.2.103 -->
	<!-- http://www.adobe.com/products/animate.html -->
	<SubTexture name="Down0000" x="0" y="0" width="1053" height="892" frameX="-5" frameY="0" frameWidth="1072" frameHeight="1000"/>
	<SubTexture name="Down0001" x="1103" y="0" width="1053" height="836" frameX="-5" frameY="-58" frameWidth="1072" frameHeight="1000"/>
	<SubTexture name="Down0002" x="2206" y="0" width="1060" height="749" frameX="-2" frameY="-154" frameWidth="1072" frameHeight="1000"/>
	<SubTexture name="Down0003" x="2206" y="0" width="1060" height="749" frameX="-2" frameY="-154" frameWidth="1072" frameHeight="1000"/>
	<SubTexture name="Down0004" x="3316" y="0" width="1068" height="764" frameX="0" frameY="-203" frameWidth="1072" frameHeight="1000"/>
	<SubTexture name="Down0005" x="3316" y="0" width="1068" height="764" frameX="0" frameY="-203" frameWidth="1072" frameHeight="1000"/>
	<SubTexture name="Down0006" x="4434" y="0" width="1063" height="763" frameX="-1" frameY="-236" frameWidth="1072" frameHeight="1000"/>
	<SubTexture name="Down0007" x="4434" y="0" width="1063" height="763" frameX="-1" frameY="-236" frameWidth="1072" frameHeight="1000"/>
	<SubTexture name="Down0008" x="5547" y="0" width="1070" height="760" frameX="-2" frameY="-240" frameWidth="1072" frameHeight="1000"/>
	<SubTexture name="Down0009" x="5547" y="0" width="1070" height="760" frameX="-2" frameY="-240" frameWidth="1072" frameHeight="1000"/>
	<SubTexture name="Down0010" x="6667" y="0" width="1060" height="758" frameX="-2" frameY="-231" frameWidth="1072" frameHeight="1000"/>
	<SubTexture name="Down0011" x="6667" y="0" width="1060" height="758" frameX="-2" frameY="-231" frameWidth="1072" frameHeight="1000"/>
	<SubTexture name="Down0012" x="0" y="942" width="1057" height="758" frameX="-2" frameY="-226" frameWidth="1072" frameHeight="1000"/>
	<SubTexture name="Down0013" x="0" y="942" width="1057" height="758" frameX="-2" frameY="-226" frameWidth="1072" frameHeight="1000"/>
	<SubTexture name="Idle0000" x="1107" y="942" width="1125" height="812" frameX="-13" frameY="0" frameWidth="1138" frameHeight="880"/>
	<SubTexture name="Idle0001" x="2282" y="942" width="1125" height="812" frameX="-13" frameY="0" frameWidth="1138" frameHeight="880"/>
	<SubTexture name="Idle0002" x="3457" y="942" width="1135" height="775" frameX="0" frameY="-55" frameWidth="1138" frameHeight="880"/>
	<SubTexture name="Idle0003" x="4642" y="942" width="1135" height="775" frameX="0" frameY="-55" frameWidth="1138" frameHeight="880"/>
	<SubTexture name="Idle0004" x="5827" y="942" width="1120" height="769" frameX="-18" frameY="-96" frameWidth="1138" frameHeight="880"/>
	<SubTexture name="Idle0005" x="6997" y="942" width="1120" height="769" frameX="-18" frameY="-96" frameWidth="1138" frameHeight="880"/>
	<SubTexture name="Idle0006" x="0" y="1804" width="1112" height="763" frameX="-23" frameY="-110" frameWidth="1138" frameHeight="880"/>
	<SubTexture name="Idle0007" x="1162" y="1804" width="1112" height="763" frameX="-23" frameY="-110" frameWidth="1138" frameHeight="880"/>
	<SubTexture name="Idle0008" x="2324" y="1804" width="1116" height="757" frameX="-20" frameY="-123" frameWidth="1138" frameHeight="880"/>
	<SubTexture name="Idle0009" x="3490" y="1804" width="1116" height="757" frameX="-20" frameY="-123" frameWidth="1138" frameHeight="880"/>
	<SubTexture name="Idle0010" x="4656" y="1804" width="1108" height="762" frameX="-25" frameY="-105" frameWidth="1138" frameHeight="880"/>
	<SubTexture name="Idle0011" x="5814" y="1804" width="1108" height="762" frameX="-25" frameY="-105" frameWidth="1138" frameHeight="880"/>
	<SubTexture name="Idle0012" x="6972" y="1804" width="1103" height="774" frameX="-23" frameY="-44" frameWidth="1138" frameHeight="880"/>
	<SubTexture name="Idle0013" x="0" y="2628" width="1103" height="774" frameX="-23" frameY="-44" frameWidth="1138" frameHeight="880"/>
	<SubTexture name="Left0000" x="1153" y="2628" width="1347" height="1101" frameX="-322" frameY="-39" frameWidth="1669" frameHeight="1140"/>
	<SubTexture name="Left0001" x="2550" y="2628" width="1307" height="1039" frameX="-300" frameY="-80" frameWidth="1669" frameHeight="1140"/>
	<SubTexture name="Left0002" x="3907" y="2628" width="1201" height="1028" frameX="-118" frameY="-88" frameWidth="1669" frameHeight="1140"/>
	<SubTexture name="Left0003" x="5158" y="2628" width="1298" height="1007" frameX="-21" frameY="-60" frameWidth="1669" frameHeight="1140"/>
	<SubTexture name="Left0004" x="6506" y="2628" width="1281" height="1089" frameX="-35" frameY="-31" frameWidth="1669" frameHeight="1140"/>
	<SubTexture name="Left0005" x="0" y="3779" width="1316" height="1078" frameX="0" frameY="0" frameWidth="1669" frameHeight="1140"/>
	<SubTexture name="Left0006" x="1366" y="3779" width="1200" height="1089" frameX="-97" frameY="-2" frameWidth="1669" frameHeight="1140"/>
	<SubTexture name="Left0007" x="2616" y="3779" width="1200" height="751" frameX="-97" frameY="-340" frameWidth="1669" frameHeight="1140"/>
	<SubTexture name="Left0008" x="3866" y="3779" width="1146" height="749" frameX="-154" frameY="-319" frameWidth="1669" frameHeight="1140"/>
	<SubTexture name="Left0009" x="3866" y="3779" width="1146" height="749" frameX="-154" frameY="-319" frameWidth="1669" frameHeight="1140"/>
	<SubTexture name="Left0010" x="5062" y="3779" width="1083" height="771" frameX="-218" frameY="-234" frameWidth="1669" frameHeight="1140"/>
	<SubTexture name="Left0011" x="5062" y="3779" width="1083" height="771" frameX="-218" frameY="-234" frameWidth="1669" frameHeight="1140"/>
	<SubTexture name="Left0012" x="6195" y="3779" width="1073" height="808" frameX="-222" frameY="-183" frameWidth="1669" frameHeight="1140"/>
	<SubTexture name="Left0013" x="0" y="4918" width="1073" height="808" frameX="-222" frameY="-183" frameWidth="1669" frameHeight="1140"/>
	<SubTexture name="Right0000" x="1123" y="4918" width="1252" height="910" frameX="-20" frameY="-92" frameWidth="1272" frameHeight="1015"/>
	<SubTexture name="Right0001" x="2425" y="4918" width="1237" height="920" frameX="0" frameY="-95" frameWidth="1272" frameHeight="1015"/>
	<SubTexture name="Right0002" x="3712" y="4918" width="1156" height="903" frameX="-6" frameY="-96" frameWidth="1272" frameHeight="1015"/>
	<SubTexture name="Right0003" x="3712" y="4918" width="1156" height="903" frameX="-6" frameY="-96" frameWidth="1272" frameHeight="1015"/>
	<SubTexture name="Right0004" x="4918" y="4918" width="962" height="903" frameX="-101" frameY="-39" frameWidth="1272" frameHeight="1015"/>
	<SubTexture name="Right0005" x="4918" y="4918" width="962" height="903" frameX="-101" frameY="-39" frameWidth="1272" frameHeight="1015"/>
	<SubTexture name="Right0006" x="5930" y="4918" width="934" height="912" frameX="-141" frameY="0" frameWidth="1272" frameHeight="1015"/>
	<SubTexture name="Right0007" x="5930" y="4918" width="934" height="912" frameX="-141" frameY="0" frameWidth="1272" frameHeight="1015"/>
	<SubTexture name="Right0008" x="6914" y="4918" width="953" height="903" frameX="-105" frameY="-11" frameWidth="1272" frameHeight="1015"/>
	<SubTexture name="Right0009" x="6914" y="4918" width="953" height="903" frameX="-105" frameY="-11" frameWidth="1272" frameHeight="1015"/>
	<SubTexture name="Right0010" x="0" y="5888" width="975" height="904" frameX="-89" frameY="-17" frameWidth="1272" frameHeight="1015"/>
	<SubTexture name="Right0011" x="0" y="5888" width="975" height="904" frameX="-89" frameY="-17" frameWidth="1272" frameHeight="1015"/>
	<SubTexture name="Right0012" x="1025" y="5888" width="970" height="903" frameX="-94" frameY="-15" frameWidth="1272" frameHeight="1015"/>
	<SubTexture name="Right0013" x="1025" y="5888" width="970" height="903" frameX="-94" frameY="-15" frameWidth="1272" frameHeight="1015"/>
	<SubTexture name="Up0000" x="2045" y="5888" width="837" height="1142" frameX="-76" frameY="-9" frameWidth="1003" frameHeight="1151"/>
	<SubTexture name="Up0001" x="2932" y="5888" width="802" height="1148" frameX="-91" frameY="0" frameWidth="1003" frameHeight="1151"/>
	<SubTexture name="Up0002" x="3784" y="5888" width="855" height="1112" frameX="-62" frameY="-29" frameWidth="1003" frameHeight="1151"/>
	<SubTexture name="Up0003" x="3784" y="5888" width="855" height="1112" frameX="-62" frameY="-29" frameWidth="1003" frameHeight="1151"/>
	<SubTexture name="Up0004" x="4689" y="5888" width="964" height="1062" frameX="-17" frameY="-78" frameWidth="1003" frameHeight="1151"/>
	<SubTexture name="Up0005" x="4689" y="5888" width="964" height="1062" frameX="-17" frameY="-78" frameWidth="1003" frameHeight="1151"/>
	<SubTexture name="Up0006" x="5703" y="5888" width="998" height="1036" frameX="-2" frameY="-104" frameWidth="1003" frameHeight="1151"/>
	<SubTexture name="Up0007" x="5703" y="5888" width="998" height="1036" frameX="-2" frameY="-104" frameWidth="1003" frameHeight="1151"/>
	<SubTexture name="Up0008" x="6751" y="5888" width="1003" height="1037" frameX="0" frameY="-103" frameWidth="1003" frameHeight="1151"/>
	<SubTexture name="Up0009" x="6751" y="5888" width="1003" height="1037" frameX="0" frameY="-103" frameWidth="1003" frameHeight="1151"/>
	<SubTexture name="Up0010" x="0" y="7086" width="987" height="1046" frameX="-7" frameY="-94" frameWidth="1003" frameHeight="1151"/>
	<SubTexture name="Up0011" x="0" y="7086" width="987" height="1046" frameX="-7" frameY="-94" frameWidth="1003" frameHeight="1151"/>
	<SubTexture name="Up0012" x="1037" y="7086" width="982" height="1047" frameX="-9" frameY="-93" frameWidth="1003" frameHeight="1151"/>
	<SubTexture name="Up0013" x="1037" y="7086" width="982" height="1047" frameX="-9" frameY="-93" frameWidth="1003" frameHeight="1151"/>
</TextureAtlas>
