{
	"song": {
		"sectionLengths": [],
		"player1": "bf",
		"player2": "spong",
		"notes": [
			{
				"sectionNotes": [],
				"lengthInSteps": 16,
				"typeOfSection": 0,
				"mustHitSection": true
			},
			{
				"sectionNotes": [],
				"lengthInSteps": 16,
				"typeOfSection": 0,
				"mustHitSection": true
			},
			{
				"sectionNotes": [],
				"lengthInSteps": 16,
				"typeOfSection": 0,
				"mustHitSection": true
			},
			{
				"sectionNotes": [],
				"lengthInSteps": 16,
				"typeOfSection": 0,
				"mustHitSection": true
			},
			{
				"sectionNotes": [],
				"lengthInSteps": 16,
				"typeOfSection": 0,
				"mustHitSection": false
			},
			{
				"sectionNotes": [
					[
						13950,
						2,
						0
					],
					[
						14100,
						2,
						0
					]
				],
				"lengthInSteps": 16,
				"typeOfSection": 0,
				"mustHitSection": false
			},
			{
				"sectionNotes": [
					[
						14550,
						7,
						0
					],
					[
						14700,
						7,
						0
					],
					[
						14850,
						6,
						0
					],
					[
						15000,
						4,
						0
					],
					[
						15150,
						6,
						0
					],
					[
						15300,
						4,
						0
					],
					[
						15450,
						6,
						0
					],
					[
						15600,
						4,
						0
					],
					[
						15900,
						5,
						300
					],
					[
						16350,
						5,
						0
					]
				],
				"lengthInSteps": 28,
				"typeOfSection": 0,
				"mustHitSection": true
			},
			{
				"sectionNotes": [
					[
						16800,
						6,
						0
					],
					[
						17400,
						7,
						0
					],
					[
						17550,
						6,
						0
					],
					[
						17700,
						7,
						0
					],
					[
						17850,
						6,
						0
					],
					[
						18000,
						7,
						0
					],
					[
						18150,
						5,
						300
					],
					[
						18450,
						2,
						150
					]
				],
				"lengthInSteps": 16,
				"typeOfSection": 0,
				"mustHitSection": true
			},
			{
				"sectionNotes": [
					[
						19200,
						6,
						0
					],
					[
						19650,
						7,
						0
					],
					[
						20100,
						4,
						0
					],
					[
						20250,
						5,
						0
					],
					[
						20550,
						6,
						0
					],
					[
						20850,
						7,
						0
					],
					[
						21150,
						6,
						0
					]
				],
				"lengthInSteps": 16,
				"typeOfSection": 0,
				"mustHitSection": false
			},
			{
				"sectionNotes": [
					[
						21600,
						7,
						0
					],
					[
						21900,
						4,
						0
					],
					[
						22200,
						4,
						0
					],
					[
						22800,
						6,
						0
					],
					[
						23250,
						7,
						0
					],
					[
						23400,
						5,
						0
					],
					[
						23550,
						6,
						0
					]
				],
				"lengthInSteps": 16,
				"typeOfSection": 0,
				"mustHitSection": false
			},
			{
				"sectionNotes": [
					[
						24000,
						3,
						0
					],
					[
						24150,
						3,
						0
					],
					[
						24450,
						2,
						0
					],
					[
						24600,
						6,
						0
					],
					[
						25050,
						4,
						0
					],
					[
						25050,
						5,
						0
					],
					[
						25500,
						5,
						0
					],
					[
						25200,
						4,
						0
					],
					[
						25350,
						4,
						0
					],
					[
						25650,
						4,
						0
					],
					[
						25800,
						5,
						0
					],
					[
						25950,
						4,
						0
					],
					[
						25950,
						6,
						0
					],
					[
						26100,
						4,
						0
					],
					[
						26100,
						6,
						0
					],
					[
						26250,
						5,
						0
					],
					[
						26100,
						5,
						0
					],
					[
						26250,
						7,
						0
					],
					[
						25950,
						7,
						0
					],
					[
						25200,
						5,
						0
					],
					[
						25500,
						7,
						0
					],
					[
						25650,
						6,
						0
					],
					[
						25950,
						5,
						0
					],
					[
						25650,
						7,
						0
					],
					[
						25800,
						7,
						0
					],
					[
						25200,
						6,
						0
					],
					[
						25350,
						6,
						0
					],
					[
						25350,
						7,
						0
					]
				],
				"lengthInSteps": 16,
				"typeOfSection": 0,
				"mustHitSection": true
			},
			{
				"sectionNotes": [
					[
						26400,
						4,
						0
					],
					[
						26400,
						5,
						0
					],
					[
						26700,
						7,
						0
					],
					[
						27000,
						6,
						0
					],
					[
						27150,
						5,
						0
					],
					[
						27300,
						5,
						0
					],
					[
						27600,
						6,
						0
					],
					[
						27750,
						6,
						0
					],
					[
						27900,
						6,
						0
					],
					[
						28350,
						5,
						0
					],
					[
						28500,
						5,
						0
					],
					[
						28650,
						6,
						0
					],
					[
						28200,
						4,
						0
					],
					[
						28350,
						6,
						0
					],
					[
						28500,
						7,
						0
					],
					[
						28500,
						4,
						0
					],
					[
						28050,
						7,
						0
					],
					[
						28050,
						5,
						0
					],
					[
						27450,
						6,
						0
					],
					[
						27750,
						7,
						0
					],
					[
						28200,
						6,
						0
					],
					[
						27450,
						5,
						0
					],
					[
						27900,
						5,
						0
					],
					[
						27600,
						4,
						0
					],
					[
						27900,
						4,
						0
					],
					[
						27450,
						7,
						0
					],
					[
						27300,
						7,
						0
					],
					[
						26850,
						4,
						0
					],
					[
						27000,
						4,
						0
					],
					[
						26550,
						5,
						0
					],
					[
						26850,
						6,
						0
					],
					[
						26400,
						6,
						0
					],
					[
						26850,
						5,
						0
					],
					[
						26700,
						6,
						0
					],
					[
						26700,
						5,
						0
					],
					[
						26700,
						4,
						0
					]
				],
				"lengthInSteps": 16,
				"typeOfSection": 0,
				"mustHitSection": true
			},
			{
				"sectionNotes": [
					[
						28800,
						0,
						0
					],
					[
						28800,
						1,
						0
					],
					[
						29100,
						3,
						0
					],
					[
						29400,
						2,
						0
					],
					[
						30300,
						2,
						0
					],
					[
						30750,
						1,
						0
					],
					[
						30900,
						1,
						0
					],
					[
						31050,
						2,
						0
					],
					[
						30600,
						0,
						0
					],
					[
						30750,
						2,
						0
					],
					[
						30900,
						3,
						0
					],
					[
						30900,
						0,
						0
					],
					[
						30450,
						3,
						0
					],
					[
						30450,
						1,
						0
					],
					[
						30600,
						2,
						0
					],
					[
						30300,
						1,
						0
					],
					[
						30300,
						0,
						0
					],
					[
						29250,
						0,
						0
					],
					[
						29400,
						0,
						0
					],
					[
						28950,
						1,
						0
					],
					[
						29250,
						2,
						0
					],
					[
						28800,
						2,
						0
					],
					[
						29250,
						1,
						0
					],
					[
						29100,
						2,
						0
					],
					[
						29100,
						1,
						0
					],
					[
						29100,
						0,
						0
					],
					[
						28800,
						4,
						0
					],
					[
						28800,
						5,
						0
					],
					[
						29100,
						7,
						0
					],
					[
						29400,
						6,
						0
					],
					[
						30300,
						6,
						0
					],
					[
						30750,
						5,
						0
					],
					[
						30900,
						5,
						0
					],
					[
						31050,
						6,
						0
					],
					[
						30600,
						4,
						0
					],
					[
						30750,
						6,
						0
					],
					[
						30900,
						7,
						0
					],
					[
						30900,
						4,
						0
					],
					[
						30450,
						7,
						0
					],
					[
						30450,
						5,
						0
					],
					[
						30600,
						6,
						0
					],
					[
						30300,
						5,
						0
					],
					[
						30300,
						4,
						0
					],
					[
						29250,
						4,
						0
					],
					[
						29400,
						4,
						0
					],
					[
						28950,
						5,
						0
					],
					[
						29250,
						6,
						0
					],
					[
						28800,
						6,
						0
					],
					[
						29250,
						5,
						0
					],
					[
						29100,
						6,
						0
					],
					[
						29100,
						5,
						0
					],
					[
						29100,
						4,
						0
					]
				],
				"lengthInSteps": 16,
				"typeOfSection": 0,
				"mustHitSection": false
			},
			{
				"sectionNotes": [
					[
						31200,
						1,
						0
					],
					[
						32400,
						3,
						0
					],
					[
						31200,
						0,
						0
					],
					[
						31350,
						1,
						0
					],
					[
						31950,
						0,
						0
					],
					[
						31950,
						1,
						0
					],
					[
						31650,
						1,
						0
					],
					[
						31800,
						2,
						0
					],
					[
						31650,
						6,
						0
					],
					[
						31350,
						4,
						0
					],
					[
						31650,
						4,
						0
					],
					[
						32100,
						6,
						0
					],
					[
						32250,
						4,
						0
					],
					[
						32100,
						4,
						0
					],
					[
						32100,
						5,
						0
					],
					[
						31950,
						5,
						0
					],
					[
						31350,
						7,
						0
					],
					[
						31350,
						5,
						0
					],
					[
						32250,
						1,
						0
					],
					[
						32700,
						1,
						0
					],
					[
						32700,
						4,
						0
					],
					[
						32850,
						1,
						0
					],
					[
						32700,
						5,
						0
					],
					[
						32400,
						5,
						0
					],
					[
						32400,
						7,
						0
					],
					[
						32700,
						6,
						0
					],
					[
						32850,
						3,
						0
					],
					[
						32400,
						0,
						0
					],
					[
						32550,
						2,
						0
					],
					[
						31200,
						0,
						0
					],
					[
						31200,
						1,
						0
					],
					[
						31500,
						3,
						0
					],
					[
						31800,
						2,
						0
					],
					[
						32700,
						2,
						0
					],
					[
						33150,
						1,
						0
					],
					[
						33300,
						1,
						0
					],
					[
						33450,
						2,
						0
					],
					[
						33000,
						0,
						0
					],
					[
						33150,
						2,
						0
					],
					[
						33300,
						3,
						0
					],
					[
						33300,
						0,
						0
					],
					[
						32850,
						3,
						0
					],
					[
						32850,
						1,
						0
					],
					[
						33000,
						2,
						0
					],
					[
						32700,
						1,
						0
					],
					[
						32700,
						0,
						0
					],
					[
						31650,
						0,
						0
					],
					[
						31800,
						0,
						0
					],
					[
						31350,
						1,
						0
					],
					[
						31650,
						2,
						0
					],
					[
						31200,
						2,
						0
					],
					[
						31650,
						1,
						0
					],
					[
						31500,
						2,
						0
					],
					[
						31500,
						1,
						0
					],
					[
						31500,
						0,
						0
					],
					[
						31200,
						4,
						0
					],
					[
						31200,
						5,
						0
					],
					[
						31500,
						7,
						0
					],
					[
						31800,
						6,
						0
					],
					[
						32700,
						6,
						0
					],
					[
						33150,
						5,
						0
					],
					[
						33300,
						5,
						0
					],
					[
						33450,
						6,
						0
					],
					[
						33000,
						4,
						0
					],
					[
						33150,
						6,
						0
					],
					[
						33300,
						7,
						0
					],
					[
						33300,
						4,
						0
					],
					[
						32850,
						7,
						0
					],
					[
						32850,
						5,
						0
					],
					[
						33000,
						6,
						0
					],
					[
						32700,
						5,
						0
					],
					[
						32700,
						4,
						0
					],
					[
						31650,
						4,
						0
					],
					[
						31800,
						4,
						0
					],
					[
						31350,
						5,
						0
					],
					[
						31650,
						6,
						0
					],
					[
						31200,
						6,
						0
					],
					[
						31650,
						5,
						0
					],
					[
						31500,
						6,
						0
					],
					[
						31500,
						5,
						0
					],
					[
						31500,
						4,
						0
					]
				],
				"lengthInSteps": 16,
				"typeOfSection": 0,
				"mustHitSection": false
			},
			{
				"sectionNotes": [
					[
						33600,
						0,
						0
					],
					[
						34800,
						2,
						0
					],
					[
						33600,
						1,
						0
					],
					[
						34800,
						3,
						0
					],
					[
						33600,
						0,
						0
					],
					[
						33750,
						1,
						0
					],
					[
						34350,
						0,
						0
					],
					[
						34350,
						1,
						0
					],
					[
						34050,
						1,
						0
					],
					[
						34200,
						2,
						0
					],
					[
						34050,
						6,
						0
					],
					[
						33750,
						4,
						0
					],
					[
						34050,
						4,
						0
					],
					[
						34500,
						6,
						0
					],
					[
						34650,
						4,
						0
					],
					[
						34500,
						4,
						0
					],
					[
						34500,
						5,
						0
					],
					[
						34350,
						5,
						0
					],
					[
						33750,
						7,
						0
					],
					[
						33750,
						5,
						0
					],
					[
						34650,
						1,
						0
					],
					[
						35100,
						1,
						0
					],
					[
						35100,
						4,
						0
					],
					[
						35250,
						1,
						0
					],
					[
						35100,
						5,
						0
					],
					[
						34800,
						5,
						0
					],
					[
						34800,
						7,
						0
					],
					[
						35100,
						6,
						0
					],
					[
						35250,
						3,
						0
					],
					[
						34800,
						0,
						0
					],
					[
						34950,
						2,
						0
					],
					[
						33600,
						0,
						0
					],
					[
						33600,
						1,
						0
					],
					[
						33900,
						3,
						0
					],
					[
						34200,
						2,
						0
					],
					[
						35100,
						2,
						0
					],
					[
						35400,
						0,
						0
					],
					[
						35250,
						3,
						0
					],
					[
						35250,
						1,
						0
					],
					[
						35400,
						2,
						0
					],
					[
						35100,
						1,
						0
					],
					[
						35100,
						0,
						0
					],
					[
						34050,
						0,
						0
					],
					[
						34200,
						0,
						0
					],
					[
						33750,
						1,
						0
					],
					[
						34050,
						2,
						0
					],
					[
						33600,
						2,
						0
					],
					[
						34050,
						1,
						0
					],
					[
						33900,
						2,
						0
					],
					[
						33900,
						1,
						0
					],
					[
						33900,
						0,
						0
					],
					[
						33600,
						4,
						0
					],
					[
						33600,
						5,
						0
					],
					[
						33900,
						7,
						0
					],
					[
						34200,
						6,
						0
					],
					[
						35100,
						6,
						0
					],
					[
						35400,
						4,
						0
					],
					[
						35250,
						7,
						0
					],
					[
						35250,
						5,
						0
					],
					[
						35400,
						6,
						0
					],
					[
						35100,
						5,
						0
					],
					[
						35100,
						4,
						0
					],
					[
						34050,
						4,
						0
					],
					[
						34200,
						4,
						0
					],
					[
						33750,
						5,
						0
					],
					[
						34050,
						6,
						0
					],
					[
						33600,
						6,
						0
					],
					[
						34050,
						5,
						0
					],
					[
						33900,
						6,
						0
					],
					[
						33900,
						5,
						0
					],
					[
						33900,
						4,
						0
					]
				],
				"lengthInSteps": 16,
				"typeOfSection": 0,
				"mustHitSection": true
			},
			{
				"sectionNotes": [],
				"lengthInSteps": 16,
				"typeOfSection": 0,
				"mustHitSection": true
			},
			{
				"sectionNotes": [
					[
						39150,
						7,
						0
					],
					[
						39300,
						6,
						0
					],
					[
						39450,
						7,
						0
					],
					[
						39600,
						6,
						0
					],
					[
						39750,
						4,
						0
					],
					[
						39900,
						1,
						0
					],
					[
						40200,
						1,
						0
					],
					[
						40500,
						1,
						0
					],
					[
						40050,
						3,
						0
					],
					[
						40350,
						3,
						0
					],
					[
						40650,
						3,
						0
					]
				],
				"lengthInSteps": 16,
				"typeOfSection": 0,
				"mustHitSection": false
			},
			{
				"sectionNotes": [
					[
						40800,
						1,
						0
					],
					[
						41400,
						1,
						0
					],
					[
						40950,
						3,
						0
					],
					[
						41100,
						2,
						0
					],
					[
						41250,
						0,
						0
					],
					[
						42450,
						1,
						0
					],
					[
						43050,
						1,
						0
					],
					[
						42750,
						1,
						0
					],
					[
						42150,
						1,
						0
					]
				],
				"lengthInSteps": 16,
				"typeOfSection": 0,
				"mustHitSection": false
			},
			{
				"sectionNotes": [
					[
						43200,
						5,
						0
					],
					[
						43800,
						5,
						0
					],
					[
						43350,
						7,
						0
					],
					[
						43500,
						6,
						0
					],
					[
						43650,
						4,
						0
					],
					[
						44850,
						5,
						0
					],
					[
						45450,
						5,
						0
					],
					[
						45150,
						5,
						0
					],
					[
						44550,
						5,
						0
					],
					[
						43650,
						6,
						0
					],
					[
						43950,
						7,
						0
					],
					[
						44400,
						6,
						0
					]
				],
				"lengthInSteps": 16,
				"typeOfSection": 0,
				"mustHitSection": true
			},
			{
				"sectionNotes": [
					[
						45600,
						5,
						0
					],
					[
						46200,
						5,
						0
					],
					[
						45750,
						7,
						0
					],
					[
						45900,
						6,
						0
					],
					[
						46050,
						4,
						0
					],
					[
						47250,
						5,
						0
					],
					[
						47850,
						5,
						0
					],
					[
						47550,
						5,
						0
					],
					[
						46950,
						5,
						0
					],
					[
						46050,
						6,
						0
					],
					[
						46350,
						7,
						0
					],
					[
						46800,
						6,
						0
					]
				],
				"lengthInSteps": 16,
				"typeOfSection": 0,
				"mustHitSection": true
			},
			{
				"sectionNotes": [
					[
						48000,
						1,
						0
					],
					[
						48300,
						2,
						0
					],
					[
						48600,
						3,
						0
					],
					[
						48900,
						2,
						0
					],
					[
						49800,
						3,
						0
					]
				],
				"lengthInSteps": 16,
				"typeOfSection": 0,
				"mustHitSection": false
			},
			{
				"sectionNotes": [
					[
						50700,
						2,
						150
					],
					[
						51000,
						3,
						150
					],
					[
						51300,
						0,
						300
					],
					[
						52500,
						7,
						0
					],
					[
						52650,
						6,
						0
					]
				],
				"lengthInSteps": 16,
				"typeOfSection": 0,
				"mustHitSection": true
			},
			{
				"sectionNotes": [
					[
						52800,
						4,
						0
					],
					[
						52950,
						7,
						0
					],
					[
						53250,
						7,
						0
					],
					[
						53400,
						6,
						0
					],
					[
						53550,
						5,
						0
					],
					[
						53700,
						7,
						0
					],
					[
						54000,
						6,
						0
					],
					[
						54150,
						4,
						0
					],
					[
						54300,
						5,
						0
					],
					[
						54450,
						7,
						0
					]
				],
				"lengthInSteps": 16,
				"typeOfSection": 0,
				"mustHitSection": true
			},
			{
				"sectionNotes": [
					[
						55200,
						6,
						0
					],
					[
						55350,
						4,
						0
					],
					[
						55500,
						7,
						0
					],
					[
						55650,
						7,
						0
					],
					[
						56250,
						7,
						0
					],
					[
						56400,
						6,
						0
					],
					[
						56550,
						5,
						0
					],
					[
						56850,
						2,
						0
					],
					[
						56850,
						1,
						0
					],
					[
						56850,
						0,
						0
					],
					[
						56850,
						3,
						0
					],
					[
						57000,
						3,
						0
					],
					[
						57000,
						2,
						0
					],
					[
						57000,
						1,
						0
					],
					[
						57000,
						0,
						0
					],
					[
						57150,
						0,
						0
					],
					[
						57150,
						1,
						0
					],
					[
						57150,
						2,
						0
					],
					[
						57150,
						3,
						0
					]
				],
				"lengthInSteps": 16,
				"typeOfSection": 0,
				"mustHitSection": true
			},
			{
				"sectionNotes": [
					[
						57600,
						4,
						0
					],
					[
						57750,
						6,
						0
					],
					[
						57900,
						4,
						0
					],
					[
						57750,
						5,
						0
					],
					[
						58050,
						7,
						0
					],
					[
						58200,
						4,
						0
					],
					[
						58350,
						5,
						0
					],
					[
						58500,
						5,
						0
					],
					[
						58650,
						6,
						0
					],
					[
						58800,
						7,
						0
					]
				],
				"lengthInSteps": 16,
				"typeOfSection": 0,
				"mustHitSection": true
			},
			{
				"sectionNotes": [],
				"lengthInSteps": 16,
				"typeOfSection": 0,
				"mustHitSection": true
			},
			{
				"sectionNotes": [
					[
						62400,
						4,
						0
					],
					[
						62550,
						5,
						0
					],
					[
						62700,
						6,
						0
					],
					[
						62850,
						7,
						0
					],
					[
						63000,
						6,
						0
					],
					[
						63150,
						5,
						0
					],
					[
						63300,
						4,
						0
					],
					[
						63450,
						5,
						0
					],
					[
						63600,
						6,
						0
					],
					[
						63750,
						7,
						0
					],
					[
						63900,
						6,
						0
					],
					[
						64050,
						7,
						0
					],
					[
						64200,
						6,
						0
					],
					[
						64350,
						7,
						0
					],
					[
						64650,
						4,
						0
					],
					[
						64500,
						5,
						0
					]
				],
				"lengthInSteps": 16,
				"typeOfSection": 0,
				"mustHitSection": true
			},
			{
				"typeOfSection": 0,
				"sectionNotes": [
					[
						64800,
						4,
						0
					],
					[
						64950,
						5,
						0
					],
					[
						65100,
						6,
						0
					],
					[
						65250,
						7,
						0
					],
					[
						65400,
						6,
						0
					],
					[
						65550,
						5,
						0
					],
					[
						65700,
						4,
						0
					],
					[
						65850,
						5,
						0
					],
					[
						66000,
						6,
						0
					],
					[
						66150,
						7,
						0
					],
					[
						66300,
						6,
						0
					],
					[
						66450,
						7,
						0
					],
					[
						66600,
						6,
						0
					],
					[
						66750,
						7,
						0
					],
					[
						67050,
						4,
						0
					],
					[
						66900,
						5,
						0
					]
				],
				"lengthInSteps": 16,
				"bpm": 100,
				"changeBPM": false,
				"mustHitSection": true
			},
			{
				"lengthInSteps": 16,
				"altAnim": false,
				"typeOfSection": 0,
				"sectionNotes": [
					[
						67200,
						0,
						0
					],
					[
						67350,
						1,
						0
					],
					[
						67500,
						2,
						0
					],
					[
						67650,
						3,
						0
					],
					[
						67800,
						2,
						0
					],
					[
						67950,
						1,
						0
					],
					[
						68100,
						0,
						0
					],
					[
						68250,
						1,
						0
					],
					[
						68400,
						2,
						0
					],
					[
						68550,
						3,
						0
					],
					[
						68700,
						2,
						0
					],
					[
						68850,
						3,
						0
					],
					[
						69000,
						2,
						0
					],
					[
						69150,
						3,
						0
					],
					[
						69450,
						0,
						0
					],
					[
						69300,
						1,
						0
					]
				],
				"bpm": 100,
				"changeBPM": false,
				"mustHitSection": true
			},
			{
				"lengthInSteps": 16,
				"altAnim": false,
				"typeOfSection": 0,
				"sectionNotes": [
					[
						69600,
						0,
						0
					],
					[
						69750,
						2,
						0
					],
					[
						69900,
						0,
						0
					],
					[
						70050,
						2,
						0
					],
					[
						70200,
						0,
						0
					],
					[
						70350,
						3,
						0
					],
					[
						70500,
						0,
						0
					],
					[
						70650,
						3,
						0
					],
					[
						70800,
						0,
						0
					]
				],
				"bpm": 100,
				"changeBPM": false,
				"mustHitSection": true
			}
		],
		"player3": "gf",
		"song": "punch-bop",
		"validScore": true,
		"sections": 0,
		"needsVoices": false,
		"speed": 1,
		"bpm": 100
	}
}